modul/__init__.py
modul/arithmetic.py
pdp_arith-0.0.1.dist-info/METADATA
pdp_arith-0.0.1.dist-info/WHEEL
pdp_arith-0.0.1.dist-info/top_level.txt
pdp_arith-0.0.1.dist-info/RECORD
