Metadata-Version: 2.1
Name: pdp-arith
Version: 0.0.1
Summary: Arithmetic operations package
Requires-Python: >=3.11
